signer/ByteBuf.py
signer/Simon.py
signer/Sm3.py
signer/__init__.py
signer/argus.py
signer/gorgon.py
signer/ladon.py
signer/pkcs7_padding.py
signer/protobuf.py
signer/sign.py
pysemo-0.7.dist-info/METADATA
pysemo-0.7.dist-info/WHEEL
pysemo-0.7.dist-info/top_level.txt
pysemo-0.7.dist-info/RECORD
