Metadata-Version: 2.4
Name: PySEMO
Version: 0.7
Summary: TikTok signing library
Author: Kameran
Author-email: hh@gmail.com
License: MIT
Requires-Python: >=3.6
Requires-Dist: pycryptodome
Dynamic: author
Dynamic: author-email
Dynamic: description
Dynamic: description-content-type
Dynamic: license
Dynamic: requires-dist
Dynamic: requires-python
Dynamic: summary
